{
  "Title": "Mad Max Beyond Thunderdome",
  "Year": "1985",
  "Rated": "PG-13",
  "Released": "10 Jul 1985",
  "Runtime": "107 min",
  "Genre": "Action, Adventure, Sci-Fi",
  "Director": "George Miller, George Ogilvie",
  "Writer": "Terry Hayes, George Miller, Byron Kennedy",
  "Actors": "Mel Gibson, Tina Turner, Bruce Spence",
  "Plot": "After being exiled from the most advanced town in post-apocalyptic Australia, a drifter travels with a group of abandoned children to rebel against the town's queen.",
  "Language": "English",
  "Country": "Australia",
  "Awards": "1 win & 10 nominations total",
  "Poster": "https://m.media-amazon.com/images/M/MV5BMTNkOGZjMGMtNDI4Zi00ZDBjLWJhY2UtMzA2YWI1ZGI5OWVhXkEyXkFqcGc@._V1_SX300.jpg",
  "Ratings": [
    {
      "Source": "Internet Movie Database",
      "Value": "6.2/10"
    },
    {
      "Source": "Rotten Tomatoes",
      "Value": "81%"
    },
    {
      "Source": "Metacritic",
      "Value": "71/100"
    }
  ],
  "Metascore": "71",
  "imdbRating": "6.2",
  "imdbVotes": "156,570",
  "imdbID": "tt0089530",
  "Type": "movie",
  "DVD": "N/A",
  "BoxOffice": "$36,230,219",
  "Production": "N/A",
  "Website": "N/A",
  "Response": "True",
  "Source": "loftet_01"
}
